doitforme/__init__.py
doitforme/agent.py
doitforme/main.py
doitforme-1.0.3.dist-info/METADATA
doitforme-1.0.3.dist-info/WHEEL
doitforme-1.0.3.dist-info/entry_points.txt
doitforme-1.0.3.dist-info/RECORD
