Metadata-Version: 2.1
Name: doitforme
Version: 1.0.3
Summary: Abuse AI to do your work
Author: Kokonico
Author-email: kokonico@duck.com
Requires-Python: >=3.12,<4.0
Classifier: Programming Language :: Python :: 3
Classifier: Programming Language :: Python :: 3.12
Classifier: Programming Language :: Python :: 3.13
Requires-Dist: ollama (>=0.3.3,<0.4.0)
